djangocms_htmlsitemap/__init__.py
djangocms_htmlsitemap/apps.py
djangocms_htmlsitemap/cms_plugins.py
djangocms_htmlsitemap/locale/fr/LC_MESSAGES/django.mo
djangocms_htmlsitemap/locale/fr/LC_MESSAGES/django.po
djangocms_htmlsitemap/migrations/0001_initial.py
djangocms_htmlsitemap/migrations/0002_auto_20180228_1210.py
djangocms_htmlsitemap/migrations/0003_alter_htmlsitemappluginconf_in_navigation.py
djangocms_htmlsitemap/migrations/__init__.py
djangocms_htmlsitemap/models.py
djangocms_htmlsitemap/templates/djangocms_htmlsitemap/sitemap.html
djangocms_htmlsitemap-2.0.0.dist-info/METADATA
djangocms_htmlsitemap-2.0.0.dist-info/WHEEL
djangocms_htmlsitemap-2.0.0.dist-info/licenses/LICENSE
djangocms_htmlsitemap-2.0.0.dist-info/RECORD
