Metadata-Version: 2.4
Name: djangocms-htmlsitemap
Version: 2.0.0
Summary: A Django CMS plugin for building HTML sitemaps showing organized lists of CMS pages.
License: BSD-3-Clause
License-File: LICENSE
Author: Kapt dev team
Author-email: dev@kapt.mobi
Requires-Python: >=3.9,<4
Classifier: License :: OSI Approved :: BSD License
Classifier: Programming Language :: Python :: 3
Classifier: Programming Language :: Python :: 3.9
Classifier: Programming Language :: Python :: 3.10
Classifier: Programming Language :: Python :: 3.11
Classifier: Programming Language :: Python :: 3.12
Classifier: Programming Language :: Python :: 3.13
Classifier: Programming Language :: Python :: 3.14
Requires-Dist: Django (>=3)
Requires-Dist: django-cms (>=3.8)
Project-URL: Repository, https://gitlab.com/kapt/open-source/djangocms-htmlsitemap
